vibeAI1/__init__.py
vibeAI1/vibelibarycode.py
vibeAI1-1.0.1.dist-info/METADATA
vibeAI1-1.0.1.dist-info/WHEEL
vibeAI1-1.0.1.dist-info/top_level.txt
vibeAI1-1.0.1.dist-info/RECORD
