Metadata-Version: 2.1
Name: vibeAI1
Version: 1.0.1
Summary: A library for predicting and blocking suspicious traffic
Author: Vibe AI
Author-email: contactvibe615@gmail.com
Classifier: Programming Language :: Python :: 3
Classifier: License :: OSI Approved :: MIT License
Classifier: Operating System :: OS Independent
Requires-Dist: numpy
Requires-Dist: pandas
Requires-Dist: pydantic
